README.md
setup.cfg
setup.py
dimitar_test/Binomialdistribution.py
dimitar_test/Gaussiandistribution.py
dimitar_test/Generaldistribution.py
dimitar_test/__init__.py
dimitar_test.egg-info/PKG-INFO
dimitar_test.egg-info/SOURCES.txt
dimitar_test.egg-info/dependency_links.txt
dimitar_test.egg-info/not-zip-safe
dimitar_test.egg-info/top_level.txt